{"cameraMode":{"drawMode":0,"name":"Shaded","section":"Shading Mode"},"sceneLighting":true,"audioPlay":false,"sceneViewState":{"m_AlwaysRefresh":false,"showFog":true,"showSkybox":true,"showFlares":true,"showImageEffects":true,"showParticleSystems":true,"showVisualEffectGraphs":true,"m_FxEnabled":true},"in2DMode":false,"pivot":{"x":155.92703247070313,"y":-110.89262390136719,"z":12.114364624023438},"rotation":{"x":0.19116266071796418,"y":0.7945107221603394,"z":-0.483095645904541,"w":0.3143969774246216},"size":279.8847961425781,"orthographic":false}